allele/__init__.py
allele/agent.py
allele/evolution.py
allele/exceptions.py
allele/genome.py
allele/kraken_lnn.py
allele/types.py
allele-1.0.1.dist-info/METADATA
allele-1.0.1.dist-info/WHEEL
allele-1.0.1.dist-info/licenses/LICENSE
allele-1.0.1.dist-info/RECORD
