Metadata-Version: 2.4
Name: allele
Version: 1.0.1
Summary: Phylogenic AI Agents - Beyond Prompt Engineering. Evolve Genetically Optimized Personalities with Liquid Memory.
Project-URL: Homepage, https://github.com/bravetto/allele
Project-URL: Documentation, https://github.com/bravetto/allele#readme
Project-URL: Repository, https://github.com/bravetto/allele
Project-URL: Issues, https://github.com/bravetto/allele/issues
Project-URL: Changelog, https://github.com/bravetto/allele/blob/main/CHANGELOG.md
Author-email: Jimmy De Jesus <jimmydejesus1129@gmail.com>
Maintainer-email: Jimmy De Jesus <jimmydejesus1129@gmail.com>
License: MIT
License-File: LICENSE
Keywords: agents,ai,allele,evolution,genetic-algorithms,genome,liquid-neural-networks,llm,neuromorphic,phylogenic
Classifier: Development Status :: 4 - Beta
Classifier: Intended Audience :: Developers
Classifier: Intended Audience :: Science/Research
Classifier: License :: OSI Approved :: MIT License
Classifier: Operating System :: OS Independent
Classifier: Programming Language :: Python :: 3
Classifier: Programming Language :: Python :: 3.8
Classifier: Programming Language :: Python :: 3.9
Classifier: Programming Language :: Python :: 3.10
Classifier: Programming Language :: Python :: 3.11
Classifier: Programming Language :: Python :: 3.12
Classifier: Topic :: Scientific/Engineering :: Artificial Intelligence
Classifier: Topic :: Software Development :: Libraries :: Python Modules
Requires-Python: >=3.8
Requires-Dist: numpy>=1.21.0
Requires-Dist: typing-extensions>=4.0.0; python_version < '3.11'
Provides-Extra: all
Requires-Dist: aiohttp>=3.8.0; extra == 'all'
Requires-Dist: anthropic>=0.18.0; extra == 'all'
Requires-Dist: openai>=1.0.0; extra == 'all'
Provides-Extra: anthropic
Requires-Dist: anthropic>=0.18.0; extra == 'anthropic'
Provides-Extra: dev
Requires-Dist: black>=23.0.0; extra == 'dev'
Requires-Dist: isort>=5.11.0; extra == 'dev'
Requires-Dist: mypy>=1.0.0; extra == 'dev'
Requires-Dist: pylint>=2.15.0; extra == 'dev'
Requires-Dist: pytest-asyncio>=0.21.0; extra == 'dev'
Requires-Dist: pytest-cov>=4.0.0; extra == 'dev'
Requires-Dist: pytest>=7.0.0; extra == 'dev'
Provides-Extra: ollama
Requires-Dist: aiohttp>=3.8.0; extra == 'ollama'
Provides-Extra: openai
Requires-Dist: openai>=1.0.0; extra == 'openai'
